LICENSE
MANIFEST.in
README.md
setup.cfg
setup.py
nb/nb.py
nb/version.py
nb/tf/__init__.py
nb/torch/backbones/efficientformer.py
nb/torch/backbones/efficientformer_custom.py
nb/torch/backbones/ghostnet.py
nb/torch/backbones/mobileone.py
nb/torch/backbones/mobileone_apple.py
nb/torch/backbones/mobileone_fb.py
nb/torch/backbones/spinenet.py
nb/torch/base/__init__.py
nb/torch/base/act.py
nb/torch/base/conv.py
nb/torch/base/conv_ws.py
nb/torch/base/norm.py
nb/torch/base/weight_init.py
nb/torch/blocks/__init__.py
nb/torch/blocks/asff_blocks.py
nb/torch/blocks/attention_blocks.py
nb/torch/blocks/bottleneck_blocks.py
nb/torch/blocks/common.py
nb/torch/blocks/conv_blocks.py
nb/torch/blocks/csp_blocks.py
nb/torch/blocks/hard_blocks.py
nb/torch/blocks/head_blocks.py
nb/torch/blocks/trans_blocks.py
nb/torch/utils/__init__.py
nb/torch/utils/checkpoint.py
nb/torch/utils/common.py
nb/torch/utils/helper.py
nb/torch/utils/initializers.py
nb/torch/utils/iter_utils.py
nb/torch/utils/utils.py
nbnb.egg-info/PKG-INFO
nbnb.egg-info/SOURCES.txt
nbnb.egg-info/dependency_links.txt
nbnb.egg-info/entry_points.txt
nbnb.egg-info/requires.txt
nbnb.egg-info/top_level.txt