Metadata-Version: 2.1
Name: nbnb
Version: 0.1.4
Summary: nb is nerual network builder for quick network prototyping
Home-page: https://github.com/jinfagang/nb
Author: Lucas Jin
Author-email: jinfagang19@163.com
License: Apache 2.0
Keywords: deep learning,neural network,builder
Platform: any
License-File: LICENSE
